dtu_config/DTU_config.py
dtu_config/__init__.py
dtu_config/_version.py
dtu_config-0.2.0.dist-info/LICENSE
dtu_config-0.2.0.dist-info/METADATA
dtu_config-0.2.0.dist-info/WHEEL
dtu_config-0.2.0.dist-info/top_level.txt
dtu_config-0.2.0.dist-info/RECORD
