Metadata-Version: 2.1
Name: dtu_config
Version: 0.2.0
Summary: A library to add a configuration file to your project
Author-email: DTU Wind Energy <neda@dtu.dk>
License: BSD-3-Clause
Project-URL: homepage, https://www.wasp.dk/
Classifier: Programming Language :: Python :: 3
Classifier: License :: OSI Approved :: BSD License
Classifier: Operating System :: OS Independent
Requires-Python: >=3.10
License-File: LICENSE
Requires-Dist: appdirs <2,>=1
Requires-Dist: email-validator >=2
Requires-Dist: phonenumbers <9,>=8
Requires-Dist: pydantic <3,>=2
Provides-Extra: dev
Requires-Dist: ipython >=7 ; extra == 'dev'
Requires-Dist: pre-commit >=2 ; extra == 'dev'
Requires-Dist: pytest >=6 ; extra == 'dev'
Requires-Dist: pytest-cov >=3 ; extra == 'dev'
Requires-Dist: setuptools >=45 ; extra == 'dev'
Requires-Dist: setuptools-scm >=6 ; extra == 'dev'
Requires-Dist: sphinx >=4 ; extra == 'dev'
Requires-Dist: sphinx-rtd-theme >=1 ; extra == 'dev'
Requires-Dist: sphinx-argparse >=0.3 ; extra == 'dev'
